MakePath-1.0.2.dist-info/DESCRIPTION.rst
MakePath-1.0.2.dist-info/METADATA
MakePath-1.0.2.dist-info/RECORD
MakePath-1.0.2.dist-info/WHEEL
MakePath-1.0.2.dist-info/metadata.json
MakePath-1.0.2.dist-info/top_level.txt
makepath/__init__.py
