Metadata-Version: 2.0
Name: MakePath
Version: 1.0.2
Summary: A small library which aims to facilitate paths building from various locations
Home-page: UNKNOWN
Author: Olivier Kozak
Author-email: olivier.kozak@gmail.com
License: GNU LGPL v3
Platform: UNKNOWN
